LICENSE
MANIFEST.in
README.rst
VERSION
requirements.txt
setup.py
src/cdumay_rest_client/__init__.py
src/cdumay_rest_client/client.py
src/cdumay_rest_client.egg-info/PKG-INFO
src/cdumay_rest_client.egg-info/SOURCES.txt
src/cdumay_rest_client.egg-info/dependency_links.txt
src/cdumay_rest_client.egg-info/requires.txt
src/cdumay_rest_client.egg-info/top_level.txt
src/cdumay_rest_client.egg-info/zip-safe
src/cdumay_rest_client/tests/__init__.py
src/cdumay_rest_client/tests/test_base.py