Metadata-Version: 2.1
Name: cdumay-rest-client
Version: 0.2.6
Summary: HTTP client
Home-page: https://github.com/cdumay/cdumay-rest-client
Author: Cedric DUMAY
Author-email: cedric.dumay@gmail.com
License: Apache License
Platform: UNKNOWN
Classifier: Programming Language :: Python
Provides-Extra: opentracing
License-File: LICENSE
